[
  {
    "outputType": {
      "type": "APK"
    },
    "apkInfo": {
      "type": "MAIN",
      "splits": [],
      "versionCode": 5,
      "versionName": "0.2.1",
      "enabled": true,
      "outputFile": "CameraMaskDemo.apk",
      "fullName": "release",
      "baseName": "release",
      "content": "\n1、optimize CameraLensView, add attrs:\nclvCameraLensWidth：相机镜头（或扫描框）宽度\nclvCameraLensHeight：相机镜头（或扫描框）高\nclvCameraLensGravity(`top`、`center`、`bottom`)：相机镜头（或扫描框）位置\nclvShowBoxAngle：是否显示扫描框四个角"
    },
    "path": "CameraMaskDemo.apk",
    "properties": {}
  }
]